LICENSE
README.md
setup.py
bom_analyzer/__init__.py
bom_analyzer/caller.py
bom_analyzer.egg-info/PKG-INFO
bom_analyzer.egg-info/SOURCES.txt
bom_analyzer.egg-info/dependency_links.txt
bom_analyzer.egg-info/requires.txt
bom_analyzer.egg-info/top_level.txt
bom_analyzer/analysis/__init__.py
bom_analyzer/analysis/cluster.py
bom_analyzer/analysis/optimization.py
bom_analyzer/analysis/outlier_detection.py
bom_analyzer/data/__init__.py
bom_analyzer/data/archive.py
bom_analyzer/data/preprocess.py
bom_analyzer/visualization/__init__.py
bom_analyzer/visualization/graph.py