Metadata-Version: 2.1
Name: bom_analyzer
Version: 2.3
Summary: Bill of Materials outlier analysis using unsupervised machine learning.
License-File: LICENSE
Requires-Dist: numpy
Requires-Dist: pandas
Requires-Dist: sentence_transformers
Requires-Dist: matplotlib
Requires-Dist: umap-learn
Requires-Dist: hdbscan
Requires-Dist: scikit-learn
Requires-Dist: optuna
Requires-Dist: tqdm
